Forthon/Forthon.c
Forthon/Forthon.h
Forthon/ForthonTimer.py
Forthon/Forthon_builder.py
Forthon/Forthon_options.py
Forthon/License.txt
Forthon/_Forthon.py
Forthon/__init__.py
Forthon/cfinterface.py
Forthon/compilers.py
Forthon/fvars.py
Forthon/interfaceparser.py
Forthon/npy_2_compat.h
Forthon/preprocess.py
Forthon/version.py
Forthon/wrappergen_derivedtypes.py
Forthon/wrappergenerator.py
Forthon/wrappergenerator_ompextension.py
forthon-0.10.10.dist-info/METADATA
forthon-0.10.10.dist-info/WHEEL
forthon-0.10.10.dist-info/entry_points.txt
forthon-0.10.10.dist-info/top_level.txt
forthon-0.10.10.dist-info/RECORD
