Metadata-Version: 2.4
Name: Forthon
Version: 0.10.10
Summary: Fortran95 wrapper/code development package
Author-email: "David P. Grote" <grote1@llnl.gov>
License: Copyright (c) 2012, Lawrence Livermore National Security, LLC.
Project-URL: Repository, https://github.com/dpgrote/Forthon.git
Classifier: Programming Language :: Python :: 3
Classifier: Development Status :: 5 - Production/Stable
Classifier: Natural Language :: English
Classifier: Environment :: Console
Classifier: Intended Audience :: Science/Research
Classifier: License :: Free To Use But Restricted
Classifier: Operating System :: OS Independent
Classifier: Topic :: Software Development :: Build Tools
Classifier: Programming Language :: Python :: 3.9
Classifier: Programming Language :: Python :: 3.10
Classifier: Programming Language :: Python :: 3.11
Classifier: Programming Language :: Python :: 3.12
Classifier: Programming Language :: Python :: 3.13
Requires-Python: >=3.9
Requires-Dist: numpy
